LICENSE
README.md
setup.py
whistleaio/__init__.py
whistleaio/client.py
whistleaio/const.py
whistleaio/exceptions.py
whistleaio/model.py
whistleaio.egg-info/PKG-INFO
whistleaio.egg-info/SOURCES.txt
whistleaio.egg-info/dependency_links.txt
whistleaio.egg-info/requires.txt
whistleaio.egg-info/top_level.txt